erasudy/__init__.py
erasudy/algorithms.py
erasudy/commands.py
erasudy/config.py
erasudy/main.py
erasudy/validations.py
erasudy-0.1.0b1.dist-info/entry_points.txt
erasudy-0.1.0b1.dist-info/WHEEL
erasudy-0.1.0b1.dist-info/METADATA
erasudy-0.1.0b1.dist-info/RECORD
