Metadata-Version: 2.1
Name: erasudy
Version: 0.1.0b1
Summary: A tool for securely erasing data
Author: blkpws
Author-email: blkpws@blackpaws.me
Requires-Python: >=3.10,<4.0
Classifier: Programming Language :: Python :: 3
Classifier: Programming Language :: Python :: 3.10
Requires-Dist: pydantic (>=1.10.2,<2.0.0)
